SRPseq-0.0.data/scripts/srpseq
src/__init__.py
src/build.py
src/consts.py
src/lr.py
src/pipeline.py
src/tree.py
src/helpers/__init__.py
src/helpers/model.py
src/helpers/pipeline.py
src/helpers/plots.py
src/utils/__init__.py
src/utils/common.py
SRPseq-0.0.dist-info/LICENSE
SRPseq-0.0.dist-info/METADATA
SRPseq-0.0.dist-info/WHEEL
SRPseq-0.0.dist-info/top_level.txt
SRPseq-0.0.dist-info/RECORD
